docstring_utils/__init__.py
docstring_utils/parsed_docstring.py
docstring_utils/parser.py
docstring_utils/utils.py
docstring_utils-1.0.0.dist-info/LICENSE
docstring_utils-1.0.0.dist-info/METADATA
docstring_utils-1.0.0.dist-info/WHEEL
docstring_utils-1.0.0.dist-info/top_level.txt
docstring_utils-1.0.0.dist-info/RECORD
